[
   [
      {
         "name":"36e08f7a-d0a9-11e5-9937-c81f66f41162",
         "components":[

         ],
         "resource_type":"lease",
         "account":{
            "name":"onelab.upmc.openlabdemo",
            "resource_type":"account",
            "valid_until":"2016-02-11T13:52:32Z",
            "created_at":"2016-02-03T15:48:50Z",
            "uuid":"fc463817-a798-4517-b958-53d55f7716a0",
            "urn":"urn:publicid:IDN+onelab:upmc+slice+openlabdemo"
         },
         "valid_until":"2016-02-11T10:30:00Z",
         "status":"active",
         "valid_from":"2016-02-11T10:21:29Z",
         "urn":"urn:publicid:IDN+r2lab+lease+36e08f7a-d0a9-11e5-9937-c81f66f41162",
         "uuid":"139707c7-32e1-4d8c-95cb-ad5420a39def"
      },
      {
         "name":"c92049b6-d0a9-11e5-9937-c81f66f41162",
         "components":[

         ],
         "resource_type":"lease",
         "account":{
            "name":"onelab.upmc.openlabdemo",
            "resource_type":"account",
            "valid_until":"2016-02-11T13:52:32Z",
            "created_at":"2016-02-03T15:48:50Z",
            "uuid":"fc463817-a798-4517-b958-53d55f7716a0",
            "urn":"urn:publicid:IDN+onelab:upmc+slice+openlabdemo"
         },
         "valid_until":"2016-02-11T14:35:00Z",
         "status":"pending",
         "valid_from":"2016-02-11T14:30:00Z",
         "urn":"urn:publicid:IDN+r2lab+lease+c92049b6-d0a9-11e5-9937-c81f66f41162",
         "uuid":"6a28b936-d15d-4789-98e6-3c1f6e849004"
      },
      {
         "components":[

         ],
         "resource_type":"lease",
         "account":{
            "name":"onelab.inria.mario.tutorial",
            "resource_type":"account",
            "valid_until":"2016-02-10T13:46:31Z",
            "created_at":"2016-02-01T14:25:19Z",
            "uuid":"ec118f9a-f3f4-43a8-ac04-e74fc7b67741",
            "urn":"urn:publicid:IDN+onelab:inria:mario+slice+tutorial"
         },
         "valid_until":"2016-02-11T14:30:00Z",
         "client_id":"30404c02-d8ed-4caf-9eeb-fb822fb90fc0",
         "status":"pending",
         "valid_from":"2016-02-11T13:00:00Z",
         "urn":"urn:publicid:IDN+r2lab+lease+4bbe6952-86cf-42a4-bd73-8349c6527d18",
         "uuid":"4bbe6952-86cf-42a4-bd73-8349c6527d18"
      },
      {
         "components":[
            {
               "name":"37nodes",
               "resource_type":"node",
               "domain":"r2lab",
               "exclusive":true,
               "available":true,
               "status":"unknown",
               "uuid":"a06d4611-48e3-4237-a800-1014777af12e",
               "urn":"urn:publicid:IDN+r2lab+node+37nodes"
            }
         ],
         "resource_type":"lease",
         "account":{
            "name":"onelab.inria.mario.script",
            "resource_type":"account",
            "valid_until":"2016-03-12T15:33:18Z",
            "created_at":"2016-01-27T10:48:56Z",
            "uuid":"6476b81a-91ad-420c-8313-845a9451963b",
            "urn":"urn:publicid:IDN+onelab:inria:mario+slice+script"
         },
         "valid_until":"2016-02-11T18:30:00Z",
         "client_id":"af56d616-ed26-41b0-956d-b02736e58c52",
         "status":"accepted",
         "valid_from":"2016-02-11T17:30:00Z",
         "urn":"urn:publicid:IDN+r2lab+lease+93433e57-2996-475b-ba6e-e10ee9193f69",
         "uuid":"93433e57-2996-475b-ba6e-e10ee9193f69"
      },
      {
         "components":[
            {
               "name":"37nodes",
               "resource_type":"node",
               "domain":"r2lab",
               "exclusive":true,
               "available":true,
               "status":"unknown",
               "uuid":"a06d4611-48e3-4237-a800-1014777af12e",
               "urn":"urn:publicid:IDN+r2lab+node+37nodes"
            }
         ],
         "resource_type":"lease",
         "account":{
            "name":"onelab.inria.mario.script",
            "resource_type":"account",
            "valid_until":"2016-03-12T15:33:18Z",
            "created_at":"2016-01-27T10:48:56Z",
            "uuid":"6476b81a-91ad-420c-8313-845a9451963b",
            "urn":"urn:publicid:IDN+onelab:inria:mario+slice+script"
         },
         "valid_until":"2016-02-12T15:00:00Z",
         "client_id":"dd71f52f-1587-490c-8fb4-8d4421bc519d",
         "status":"accepted",
         "valid_from":"2016-02-12T14:00:00Z",
         "urn":"urn:publicid:IDN+r2lab+lease+31ffe2fb-b43a-41d2-8baf-7ff0bdb7eac0",
         "uuid":"31ffe2fb-b43a-41d2-8baf-7ff0bdb7eac0"
      },
      {
         "components":[
            {
               "name":"37nodes",
               "resource_type":"node",
               "domain":"r2lab",
               "exclusive":true,
               "available":true,
               "status":"unknown",
               "uuid":"a06d4611-48e3-4237-a800-1014777af12e",
               "urn":"urn:publicid:IDN+r2lab+node+37nodes"
            }
         ],
         "resource_type":"lease",
         "account":{
            "name":"onelab.inria.mario.script",
            "resource_type":"account",
            "valid_until":"2016-03-12T15:33:18Z",
            "created_at":"2016-01-27T10:48:56Z",
            "uuid":"6476b81a-91ad-420c-8313-845a9451963b",
            "urn":"urn:publicid:IDN+onelab:inria:mario+slice+script"
         },
         "valid_until":"2016-02-12T16:00:00Z",
         "client_id":"dd71f52f-1587-490c-8fb4-8d4421bc519d",
         "status":"accepted",
         "valid_from":"2016-02-12T15:00:00Z",
         "urn":"urn:publicid:IDN+r2lab+lease+31ffe2fb-b43a-41d2-8baf-7ff0bdb7eac0",
         "uuid":"31ffe2fb-b43a-41d2-8baf-7ff0bdb7eac0"
      },
      {
         "components":[
            {
               "name":"37nodes",
               "resource_type":"node",
               "domain":"r2lab",
               "exclusive":true,
               "available":true,
               "status":"unknown",
               "uuid":"a06d4611-48e3-4237-a800-1014777af12e",
               "urn":"urn:publicid:IDN+r2lab+node+37nodes"
            }
         ],
         "resource_type":"lease",
         "account":{
            "name":"onelab.inria.mario.script",
            "resource_type":"account",
            "valid_until":"2016-03-12T15:33:18Z",
            "created_at":"2016-01-27T10:48:56Z",
            "uuid":"6476b81a-91ad-420c-8313-845a9451963b",
            "urn":"urn:publicid:IDN+onelab:inria:mario+slice+script"
         },
         "valid_until":"2016-02-12T18:00:00Z",
         "client_id":"dd71f52f-1587-490c-8fb4-8d4421bc519d",
         "status":"accepted",
         "valid_from":"2016-02-12T17:00:00Z",
         "urn":"urn:publicid:IDN+r2lab+lease+31ffe2fb-b43a-41d2-8baf-7ff0bdb7eac0",
         "uuid":"31ffe2fb-b43a-41d2-8baf-7ff0bdb7eac0"
      },
      {
         "components":[
            {
               "name":"37nodes",
               "resource_type":"node",
               "domain":"r2lab",
               "exclusive":true,
               "available":true,
               "status":"unknown",
               "uuid":"a0daf14c-0821-435d-a710-c29988045ff0",
               "urn":"urn:publicid:IDN+r2lab+node+37nodes"
            }
         ],
         "resource_type":"lease",
         "account":{
            "name":"onelab.inria.r2lab.mario_test",
            "resource_type":"account",
            "valid_until":"2016-03-12T15:33:18Z",
            "created_at":"2016-02-01T14:49:16Z",
            "uuid":"13345879-2321-400d-b01b-c0a79db1ecad",
            "urn":"urn:publicid:IDN+onelab:inria:r2lab+slice+mario_test"
         },
         "valid_until":"2016-02-11T16:00:00Z",
         "client_id":"287d474f-ce9f-4113-ba32-2bf407c994d2",
         "status":"accepted",
         "valid_from":"2016-02-11T15:00:00Z",
         "urn":"urn:publicid:IDN+r2lab+lease+ef244fec-f0a4-4ca9-b69c-2f0c1ebc6363",
         "uuid":"ef244fec-f0a4-4ca9-b69c-2f0c1ebc6363"
      },
      {
         "components":[

         ],
         "resource_type":"lease",
         "account":{
            "name":"onelab.inria.r2lab.naoufal",
            "resource_type":"account",
            "valid_until":"2016-02-17T10:30:52Z",
            "created_at":"2016-01-25T09:40:06Z",
            "uuid":"374f1211-03cd-4880-80d3-67c7806ef8fe",
            "urn":"urn:publicid:IDN+onelab:inria:r2lab+slice+naoufal"
         },
         "valid_until":"2016-02-11T15:00:00Z",
         "client_id":"351d0725-fe22-4e9f-8b64-e39ab143f139",
         "status":"active",
         "valid_from":"2016-02-11T07:00:00Z",
         "urn":"urn:publicid:IDN+r2lab+lease+8875d58e-b8fe-4db5-92c4-3aa12bfeb861",
         "uuid":"8875d58e-b8fe-4db5-92c4-3aa12bfeb861"
      }
   ]
]
